elle/__init__.py
elle/lib/__init__.py
elle/lib/beam2d/__init__.py
elle/lib/beam2d/beam.py
elle-0.0.4.dist-info/AUTHORS.md
elle-0.0.4.dist-info/LICENSE
elle-0.0.4.dist-info/METADATA
elle-0.0.4.dist-info/WHEEL
elle-0.0.4.dist-info/top_level.txt
elle-0.0.4.dist-info/RECORD
