Metadata-Version: 2.2
Name: elle
Version: 0.0.4
Summary: A namespace for finite element libraries targeted at research into neural network architectures.
Author: Claudio M. Perez
Project-URL: Organization, https://veux.io
Classifier: Development Status :: 2 - Pre-Alpha
Classifier: Intended Audience :: Developers
Classifier: Operating System :: Unix
Classifier: Operating System :: POSIX
Classifier: Operating System :: Microsoft :: Windows
Classifier: Programming Language :: Python
Classifier: Programming Language :: Python :: 3
Classifier: Programming Language :: Python :: 3.6
Classifier: Programming Language :: Python :: 3.7
Classifier: Programming Language :: Python :: 3.8
Classifier: Programming Language :: Python :: Implementation :: CPython
Classifier: Programming Language :: Python :: Implementation :: PyPy
Classifier: Topic :: Utilities
Requires-Python: >=3.6
License-File: LICENSE
License-File: AUTHORS.md
Requires-Dist: opensees
Requires-Dist: veux
Provides-Extra: shellcomplete
Requires-Dist: click_completion; extra == "shellcomplete"
Provides-Extra: tensorflow
Requires-Dist: tensorflow~=2.0; extra == "tensorflow"
Requires-Dist: tensorflow-probability~=0.10; extra == "tensorflow"
Provides-Extra: jax
Requires-Dist: jax>0.1.72,~=0.1; extra == "jax"
Requires-Dist: jaxlib>0.1.51,~=0.1; extra == "jax"
Provides-Extra: backends
Requires-Dist: jaxlib>0.1.51,~=0.1; extra == "backends"
Requires-Dist: jax>0.1.72,~=0.1; extra == "backends"
Requires-Dist: tensorflow-probability~=0.10; extra == "backends"
Requires-Dist: tensorflow~=2.0; extra == "backends"
Dynamic: author
Dynamic: classifier
Dynamic: description
Dynamic: description-content-type
Dynamic: project-url
Dynamic: provides-extra
Dynamic: requires-dist
Dynamic: requires-python
Dynamic: summary
